alosi/__init__.py
alosi/api_client.py
alosi/bridge_api.py
alosi/engine.py
alosi/engine_api.py
alosi/google_drive.py
alosi/initializer.py
alosi/olx.py
alosi-2.1.1.dist-info/LICENSE.txt
alosi-2.1.1.dist-info/METADATA
alosi-2.1.1.dist-info/WHEEL
alosi-2.1.1.dist-info/top_level.txt
alosi-2.1.1.dist-info/RECORD
