Metadata-Version: 2.1
Name: alosi
Version: 2.1.1
Summary: Utilities for the ALOSI adaptive learning system
Home-page: https://github.com/harvard-vpal/alosi
Author: Andrew Ang
Author-email: andrew_ang@harvard.edu
License: Apache-2.0
Platform: UNKNOWN
Requires-Dist: requests
Requires-Dist: numpy
Provides-Extra: data
Requires-Dist: pandas; extra == 'data'
Requires-Dist: lxml; extra == 'data'
Requires-Dist: google-auth (>=1.5.0); extra == 'data'
Requires-Dist: google-auth-oauthlib (>=0.2.0); extra == 'data'
Requires-Dist: gspread (>=3.0.0); extra == 'data'
Requires-Dist: gspread-dataframe; extra == 'data'
